beta_cynosure/__init__.py
beta_cynosure/engine.py
beta_cynosure/__pycache__/__init__.cpython-313.pyc
beta_cynosure/__pycache__/engine.cpython-313.pyc
beta_cynosure/utils/cleaner.py
beta_cynosure/utils/companies_data.py
beta_cynosure/utils/downloader.py
beta_cynosure/utils/export.py
beta_cynosure/utils/loaders.py
beta_cynosure/utils/processor.py
beta_cynosure/utils/__pycache__/cleaner.cpython-313.pyc
beta_cynosure/utils/__pycache__/companies_data.cpython-313.pyc
beta_cynosure/utils/__pycache__/downloader.cpython-313.pyc
beta_cynosure/utils/__pycache__/export.cpython-313.pyc
beta_cynosure/utils/__pycache__/loaders.cpython-313.pyc
beta_cynosure/utils/__pycache__/processor.cpython-313.pyc
beta_cynosure-0.1.4.dist-info/licenses/LICENSE
beta_cynosure-0.1.4.dist-info/METADATA
beta_cynosure-0.1.4.dist-info/WHEEL
beta_cynosure-0.1.4.dist-info/entry_points.txt
beta_cynosure-0.1.4.dist-info/top_level.txt
beta_cynosure-0.1.4.dist-info/RECORD
