Metadata-Version: 2.4
Name: beta-cynosure
Version: 0.1.4
Summary: Extrator e parser de dados financeiros da CVM (DFP, ITR e FRE).
Author-email: Diego Silva Pinto <diegosilva@engineer.com>
License-Expression: MIT
Project-URL: Source, https://github.com/diehgosp/beta-cynosure
Classifier: Programming Language :: Python :: 3
Classifier: Operating System :: OS Independent
Requires-Python: >=3.8
License-File: LICENSE
Requires-Dist: pandas>=2.0.0
Requires-Dist: requests>=2.25.0
Dynamic: license-file
